downloader/__init__.py
downloader/__main__.py
downloader/downloader.py
downloader/settings.py
tests/__init__.py
tests/test_regex.py
cedl-0.1.3.dist-info/LICENSE.TXT
cedl-0.1.3.dist-info/METADATA
cedl-0.1.3.dist-info/WHEEL
cedl-0.1.3.dist-info/entry_points.txt
cedl-0.1.3.dist-info/top_level.txt
cedl-0.1.3.dist-info/RECORD
